dll_scanner/__init__.py
dll_scanner/analyzer.py
dll_scanner/cli.py
dll_scanner/cyclonedx_exporter.py
dll_scanner/metadata.py
dll_scanner/page_generator.py
dll_scanner/scanner.py
dll_scanner/wix_integration.py
dll_scanner-0.6.4.dist-info/licenses/LICENSE
dll_scanner-0.6.4.dist-info/METADATA
dll_scanner-0.6.4.dist-info/WHEEL
dll_scanner-0.6.4.dist-info/entry_points.txt
dll_scanner-0.6.4.dist-info/top_level.txt
dll_scanner-0.6.4.dist-info/RECORD
