Metadata-Version: 2.4
Name: dll-scanner
Version: 0.6.4
Summary: A Python tool to scan directories for DLL files and extract metadata
Author: DLL Scanner Contributors
License: MIT
Project-URL: Homepage, https://github.com/FlaccidFacade/dll-scanner
Project-URL: Repository, https://github.com/FlaccidFacade/dll-scanner
Project-URL: Issues, https://github.com/FlaccidFacade/dll-scanner/issues
Keywords: dll,metadata,scanner,dependencies,static-analysis
Classifier: Development Status :: 4 - Beta
Classifier: Intended Audience :: Developers
Classifier: Programming Language :: Python :: 3
Classifier: Programming Language :: Python :: 3.9
Classifier: Programming Language :: Python :: 3.10
Classifier: Programming Language :: Python :: 3.11
Classifier: Programming Language :: Python :: 3.12
Classifier: Operating System :: Microsoft :: Windows
Classifier: Operating System :: POSIX :: Linux
Classifier: Topic :: Software Development :: Libraries :: Python Modules
Classifier: Topic :: System :: Software Distribution
Requires-Python: >=3.9
License-File: LICENSE
Requires-Dist: pefile>=2023.2.7
Requires-Dist: click>=8.0.0
Requires-Dist: pathlib-mate>=1.0.0
Requires-Dist: rich>=13.0.0
Requires-Dist: cyclonedx-bom>=4.0.0
Requires-Dist: pywin32>=306; sys_platform == "win32"
Provides-Extra: dev
Requires-Dist: pytest>=7.0.0; extra == "dev"
Requires-Dist: pytest-cov>=4.0.0; extra == "dev"
Requires-Dist: black>=23.0.0; extra == "dev"
Requires-Dist: flake8>=6.0.0; extra == "dev"
Requires-Dist: mypy>=1.0.0; extra == "dev"
Requires-Dist: twine>=4.0.0; extra == "dev"
Requires-Dist: build>=0.10.0; extra == "dev"
Requires-Dist: pre-commit>=3.5.0; extra == "dev"
Dynamic: license-file
